pykozo/__init__.py
pykozo/pykozo.py
PyKozo-0.0.21.dist-info/LICENSE
PyKozo-0.0.21.dist-info/METADATA
PyKozo-0.0.21.dist-info/WHEEL
PyKozo-0.0.21.dist-info/top_level.txt
PyKozo-0.0.21.dist-info/RECORD
